<?xml version="1.0" encoding="UTF-8"?>

<FLOW VERSION="3.0" CLEANUP="true">
  <COMMENT></COMMENT>

  <!-- nodes -->

<INVOKE TIMEOUT="" SERVICE="pub.flow:savePipeline" VALIDATE-IN="$none" VALIDATE-OUT="$none">
  <COMMENT></COMMENT>

  <!-- nodes -->

<MAP MODE="INPUT">
  <MAPTARGET>

<Values version="2.0">
  <record name="xml" javaclass="com.wm.util.Values">
    <value name="node_type">record</value>
    <value name="is_public">false</value>
    <value name="field_name">savePipelineInput</value>
    <value name="field_type">record</value>
    <value name="field_dim">0</value>
    <value name="nillable">true</value>
    <value name="form_qualified">false</value>
    <value name="is_global">false</value>
    <array name="rec_fields" type="record" depth="1">
      <record javaclass="com.wm.util.Values">
        <value name="node_type">unknown</value>
        <value name="is_public">false</value>
        <value name="field_name">$name</value>
        <value name="field_type">string</value>
        <value name="field_dim">0</value>
        <value name="nillable">true</value>
        <value name="form_qualified">false</value>
        <value name="is_global">false</value>
      </record>
    </array>
    <value name="modifiable">true</value>
  </record>
</Values>
</MAPTARGET>
  <MAPSOURCE>

<Values version="2.0">
  <record name="xml" javaclass="com.wm.util.Values">
    <value name="node_type">record</value>
    <value name="is_public">false</value>
    <value name="field_type">record</value>
    <value name="field_dim">0</value>
    <value name="nillable">true</value>
    <value name="form_qualified">false</value>
    <value name="is_global">false</value>
    <array name="rec_fields" type="record" depth="1">
    </array>
    <value name="modifiable">true</value>
  </record>
</Values>
</MAPSOURCE>

  <!-- nodes -->

<MAPSET NAME="Setter" OVERWRITE="true" VARIABLES="false" FIELD="/$name;1;0">
  <DATA ENCODING="XMLValues" I18N="true">

<Values version="2.0">
  <value name="xml">importFile</value>
  <record name="type" javaclass="com.wm.util.Values">
    <value name="node_type">unknown</value>
    <value name="is_public">false</value>
    <value name="field_name">$name</value>
    <value name="field_type">string</value>
    <value name="field_dim">0</value>
    <value name="nillable">true</value>
    <value name="form_qualified">false</value>
    <value name="is_global">false</value>
  </record>
</Values>
</DATA>
</MAPSET>
</MAP>

<MAP MODE="OUTPUT">
  <MAPTARGET>

<Values version="2.0">
  <record name="xml" javaclass="com.wm.util.Values">
    <value name="node_type">record</value>
    <value name="is_public">false</value>
    <value name="field_type">record</value>
    <value name="field_dim">0</value>
    <value name="nillable">true</value>
    <value name="form_qualified">false</value>
    <value name="is_global">false</value>
    <array name="rec_fields" type="record" depth="1">
      <record javaclass="com.wm.util.Values">
        <value name="node_type">unknown</value>
        <value name="is_public">false</value>
        <value name="field_name">$name</value>
        <value name="field_type">string</value>
        <value name="field_dim">0</value>
        <value name="nillable">true</value>
        <value name="form_qualified">false</value>
        <value name="is_global">false</value>
      </record>
    </array>
    <value name="modifiable">true</value>
  </record>
</Values>
</MAPTARGET>
  <MAPSOURCE>

<Values version="2.0">
  <record name="xml" javaclass="com.wm.util.Values">
    <value name="node_type">record</value>
    <value name="is_public">false</value>
    <value name="field_type">record</value>
    <value name="field_dim">0</value>
    <value name="nillable">true</value>
    <value name="form_qualified">false</value>
    <value name="is_global">false</value>
    <array name="rec_fields" type="record" depth="1">
    </array>
    <value name="modifiable">true</value>
  </record>
</Values>
</MAPSOURCE>

  <!-- nodes -->

<MAPDELETE FIELD="/$name;1;0">
</MAPDELETE>
</MAP>
</INVOKE>

<INVOKE TIMEOUT="" SERVICE="pub.flow:restorePipeline" VALIDATE-IN="$none" VALIDATE-OUT="$none" DISABLED="true">
  <COMMENT></COMMENT>

  <!-- nodes -->

<MAP MODE="INPUT">
  <MAPTARGET>

<Values version="2.0">
  <record name="xml" javaclass="com.wm.util.Values">
    <value name="node_type">record</value>
    <value name="is_public">false</value>
    <value name="field_name">restorePipelineInput</value>
    <value name="field_type">record</value>
    <value name="field_dim">0</value>
    <value name="nillable">true</value>
    <value name="form_qualified">false</value>
    <value name="is_global">false</value>
    <array name="rec_fields" type="record" depth="1">
      <record javaclass="com.wm.util.Values">
        <value name="node_type">unknown</value>
        <value name="is_public">false</value>
        <value name="field_name">$name</value>
        <value name="field_type">string</value>
        <value name="field_dim">0</value>
        <value name="nillable">true</value>
        <value name="form_qualified">false</value>
        <value name="is_global">false</value>
      </record>
      <record javaclass="com.wm.util.Values">
        <value name="node_type">unknown</value>
        <value name="is_public">false</value>
        <value name="field_name">$merge</value>
        <value name="field_type">string</value>
        <value name="field_dim">0</value>
        <value name="field_opt">true</value>
        <array name="field_options" type="value" depth="1">
          <value>true</value>
          <value>false</value>
        </array>
        <value name="nillable">true</value>
        <value name="form_qualified">false</value>
        <value name="is_global">false</value>
      </record>
      <record javaclass="com.wm.util.Values">
        <value name="node_type">unknown</value>
        <value name="is_public">false</value>
        <value name="field_name">$remove</value>
        <value name="field_type">string</value>
        <value name="field_dim">0</value>
        <value name="field_opt">true</value>
        <array name="field_options" type="value" depth="1">
          <value>false</value>
          <value>true</value>
        </array>
        <value name="nillable">true</value>
        <value name="form_qualified">false</value>
        <value name="is_global">false</value>
      </record>
    </array>
    <value name="modifiable">true</value>
  </record>
</Values>
</MAPTARGET>
  <MAPSOURCE>

<Values version="2.0">
  <record name="xml" javaclass="com.wm.util.Values">
    <value name="node_type">record</value>
    <value name="is_public">false</value>
    <value name="field_type">record</value>
    <value name="field_dim">0</value>
    <value name="nillable">true</value>
    <value name="form_qualified">false</value>
    <value name="is_global">false</value>
    <array name="rec_fields" type="record" depth="1">
    </array>
    <value name="modifiable">true</value>
  </record>
</Values>
</MAPSOURCE>

  <!-- nodes -->

<MAPSET NAME="Setter" OVERWRITE="true" VARIABLES="false" FIELD="/$name;1;0">
  <DATA ENCODING="XMLValues" I18N="true">

<Values version="2.0">
  <value name="xml">importFile</value>
  <record name="type" javaclass="com.wm.util.Values">
    <value name="node_type">unknown</value>
    <value name="is_public">false</value>
    <value name="field_name">$name</value>
    <value name="field_type">string</value>
    <value name="field_dim">0</value>
    <value name="nillable">true</value>
    <value name="form_qualified">false</value>
    <value name="is_global">false</value>
  </record>
</Values>
</DATA>
</MAPSET>
</MAP>

<MAP MODE="OUTPUT">
  <MAPTARGET>

<Values version="2.0">
  <record name="xml" javaclass="com.wm.util.Values">
    <value name="node_type">record</value>
    <value name="is_public">false</value>
    <value name="field_type">record</value>
    <value name="field_dim">0</value>
    <value name="nillable">true</value>
    <value name="form_qualified">false</value>
    <value name="is_global">false</value>
    <array name="rec_fields" type="record" depth="1">
      <record javaclass="com.wm.util.Values">
        <value name="node_type">unknown</value>
        <value name="is_public">false</value>
        <value name="field_name">$name</value>
        <value name="field_type">string</value>
        <value name="field_dim">0</value>
        <value name="nillable">true</value>
        <value name="form_qualified">false</value>
        <value name="is_global">false</value>
      </record>
    </array>
    <value name="modifiable">true</value>
  </record>
</Values>
</MAPTARGET>
  <MAPSOURCE>

<Values version="2.0">
  <record name="xml" javaclass="com.wm.util.Values">
    <value name="node_type">record</value>
    <value name="is_public">false</value>
    <value name="field_type">record</value>
    <value name="field_dim">0</value>
    <value name="nillable">true</value>
    <value name="form_qualified">false</value>
    <value name="is_global">false</value>
    <array name="rec_fields" type="record" depth="1">
    </array>
    <value name="modifiable">true</value>
  </record>
</Values>
</MAPSOURCE>

  <!-- nodes -->

<MAPDELETE FIELD="/$name;1;0">
</MAPDELETE>
</MAP>
</INVOKE>

<INVOKE TIMEOUT="" SERVICE="pub.flatFile:convertToValues" VALIDATE-IN="$none" VALIDATE-OUT="$none">
  <COMMENT></COMMENT>

  <!-- nodes -->

<MAP MODE="INPUT">
  <MAPTARGET>

<Values version="2.0">
  <record name="xml" javaclass="com.wm.util.Values">
    <value name="node_type">record</value>
    <value name="is_public">false</value>
    <value name="field_name">convertToValuesInput</value>
    <value name="field_type">record</value>
    <value name="field_dim">0</value>
    <value name="nillable">true</value>
    <value name="form_qualified">false</value>
    <value name="is_global">false</value>
    <array name="rec_fields" type="record" depth="1">
      <record javaclass="com.wm.util.Values">
        <value name="node_type">unknown</value>
        <value name="is_public">false</value>
        <value name="field_name">ffData</value>
        <value name="field_type">object</value>
        <value name="field_dim">0</value>
        <value name="nillable">true</value>
        <value name="form_qualified">false</value>
        <value name="is_global">false</value>
      </record>
      <record javaclass="com.wm.util.Values">
        <value name="node_type">unknown</value>
        <value name="is_public">false</value>
        <value name="field_name">ffSchema</value>
        <value name="field_type">string</value>
        <value name="field_dim">0</value>
        <value name="nillable">true</value>
        <value name="form_qualified">false</value>
        <value name="is_global">false</value>
      </record>
      <record javaclass="com.wm.util.Values">
        <value name="node_type">unknown</value>
        <value name="is_public">false</value>
        <value name="field_name">ffIterator</value>
        <value name="field_type">object</value>
        <value name="field_dim">0</value>
        <value name="field_opt">true</value>
        <value name="nillable">true</value>
        <value name="form_qualified">false</value>
        <value name="is_global">false</value>
      </record>
      <record javaclass="com.wm.util.Values">
        <value name="node_type">unknown</value>
        <value name="is_public">false</value>
        <value name="field_name">encoding</value>
        <value name="field_type">string</value>
        <value name="field_dim">0</value>
        <value name="field_opt">true</value>
        <value name="nillable">true</value>
        <value name="form_qualified">false</value>
        <value name="is_global">false</value>
      </record>
      <record javaclass="com.wm.util.Values">
        <value name="node_type">record</value>
        <value name="is_public">false</value>
        <value name="field_name">delimiters</value>
        <value name="field_type">record</value>
        <value name="field_dim">0</value>
        <value name="field_opt">true</value>
        <value name="nillable">true</value>
        <value name="form_qualified">false</value>
        <value name="is_global">false</value>
        <array name="rec_fields" type="record" depth="1">
        </array>
        <value name="modifiable">true</value>
      </record>
      <record javaclass="com.wm.util.Values">
        <value name="node_type">unknown</value>
        <value name="is_public">false</value>
        <value name="field_name">iterate</value>
        <value name="field_type">string</value>
        <value name="field_dim">0</value>
        <value name="field_opt">true</value>
        <array name="field_options" type="value" depth="1">
          <value>false</value>
          <value>true</value>
        </array>
        <value name="nillable">true</value>
        <value name="form_qualified">false</value>
        <value name="is_global">false</value>
      </record>
      <record javaclass="com.wm.util.Values">
        <value name="node_type">unknown</value>
        <value name="is_public">false</value>
        <value name="field_name">createIfNull</value>
        <value name="field_type">string</value>
        <value name="field_dim">0</value>
        <value name="field_opt">true</value>
        <array name="field_options" type="value" depth="1">
          <value>true</value>
          <value>false</value>
        </array>
        <value name="nillable">true</value>
        <value name="form_qualified">false</value>
        <value name="is_global">false</value>
      </record>
      <record javaclass="com.wm.util.Values">
        <value name="node_type">unknown</value>
        <value name="is_public">false</value>
        <value name="field_name">skipWhiteSpace</value>
        <value name="field_type">string</value>
        <value name="field_dim">0</value>
        <value name="field_opt">true</value>
        <array name="field_options" type="value" depth="1">
          <value>true</value>
          <value>false</value>
        </array>
        <value name="nillable">true</value>
        <value name="form_qualified">false</value>
        <value name="is_global">false</value>
      </record>
      <record javaclass="com.wm.util.Values">
        <value name="node_type">unknown</value>
        <value name="is_public">false</value>
        <value name="field_name">keepResults</value>
        <value name="field_type">string</value>
        <value name="field_dim">0</value>
        <value name="field_opt">true</value>
        <array name="field_options" type="value" depth="1">
          <value>true</value>
          <value>false</value>
        </array>
        <value name="nillable">true</value>
        <value name="form_qualified">false</value>
        <value name="is_global">false</value>
      </record>
      <record javaclass="com.wm.util.Values">
        <value name="node_type">unknown</value>
        <value name="is_public">false</value>
        <value name="field_name">validate</value>
        <value name="field_type">string</value>
        <value name="field_dim">0</value>
        <value name="field_opt">true</value>
        <array name="field_options" type="value" depth="1">
          <value>false</value>
          <value>true</value>
        </array>
        <value name="nillable">true</value>
        <value name="form_qualified">false</value>
        <value name="is_global">false</value>
      </record>
      <record javaclass="com.wm.util.Values">
        <value name="node_type">unknown</value>
        <value name="is_public">false</value>
        <value name="field_name">returnErrors</value>
        <value name="field_type">string</value>
        <value name="field_dim">0</value>
        <value name="field_opt">true</value>
        <array name="field_options" type="value" depth="1">
          <value>asArray</value>
          <value>inResults</value>
          <value>both</value>
        </array>
        <value name="nillable">true</value>
        <value name="form_qualified">false</value>
        <value name="is_global">false</value>
      </record>
      <record javaclass="com.wm.util.Values">
        <value name="node_type">unknown</value>
        <value name="is_public">false</value>
        <value name="field_name">maxErrors</value>
        <value name="field_type">string</value>
        <value name="field_dim">0</value>
        <value name="field_opt">true</value>
        <value name="nillable">true</value>
        <value name="form_qualified">false</value>
        <value name="is_global">false</value>
      </record>
      <record javaclass="com.wm.util.Values">
        <value name="node_type">record</value>
        <record name="node_hints" javaclass="com.wm.util.Values">
          <value name="field_largerEditor">false</value>
          <value name="field_password">false</value>
        </record>
        <value name="is_public">false</value>
        <value name="field_name">flags</value>
        <value name="field_type">record</value>
        <value name="field_dim">0</value>
        <value name="field_opt">true</value>
        <value name="nillable">true</value>
        <value name="form_qualified">false</value>
        <value name="is_global">false</value>
        <array name="rec_fields" type="record" depth="1">
          <record javaclass="com.wm.util.Values">
            <value name="node_type">record</value>
            <record name="node_hints" javaclass="com.wm.util.Values">
              <value name="field_usereditable">false</value>
              <value name="field_largerEditor">false</value>
              <value name="field_password">false</value>
            </record>
            <value name="is_public">false</value>
            <value name="field_name">addRecordCount</value>
            <value name="field_type">string</value>
            <value name="field_dim">0</value>
            <array name="field_options" type="value" depth="1">
              <value>false</value>
              <value>true</value>
            </array>
            <value name="nillable">true</value>
            <value name="form_qualified">false</value>
            <value name="is_global">false</value>
          </record>
          <record javaclass="com.wm.util.Values">
            <value name="node_type">record</value>
            <record name="node_hints" javaclass="com.wm.util.Values">
              <value name="field_usereditable">false</value>
              <value name="field_largerEditor">false</value>
              <value name="field_password">false</value>
            </record>
            <value name="is_public">false</value>
            <value name="field_name">detailedErrors</value>
            <value name="field_type">string</value>
            <value name="field_dim">0</value>
            <array name="field_options" type="value" depth="1">
              <value>false</value>
              <value>true</value>
            </array>
            <value name="nillable">true</value>
            <value name="form_qualified">false</value>
            <value name="is_global">false</value>
          </record>
          <record javaclass="com.wm.util.Values">
            <value name="node_type">record</value>
            <record name="node_hints" javaclass="com.wm.util.Values">
              <value name="field_usereditable">false</value>
              <value name="field_largerEditor">false</value>
              <value name="field_password">false</value>
            </record>
            <value name="is_public">false</value>
            <value name="field_name">skipToFirstRecord</value>
            <value name="field_type">string</value>
            <value name="field_dim">0</value>
            <array name="field_options" type="value" depth="1">
              <value>true</value>
              <value>false</value>
            </array>
            <value name="nillable">true</value>
            <value name="form_qualified">false</value>
            <value name="is_global">false</value>
          </record>
          <record javaclass="com.wm.util.Values">
            <value name="node_type">record</value>
            <value name="node_comment"></value>
            <record name="node_hints" javaclass="com.wm.util.Values">
              <value name="field_usereditable">false</value>
              <value name="field_largerEditor">false</value>
              <value name="field_password">false</value>
            </record>
            <value name="is_public">false</value>
            <value name="field_name">trimWhitespace</value>
            <value name="field_type">string</value>
            <value name="field_dim">0</value>
            <array name="field_options" type="value" depth="1">
              <value>none</value>
              <value>left</value>
              <value>right</value>
              <value>both</value>
            </array>
            <value name="nillable">true</value>
            <value name="form_qualified">false</value>
            <value name="is_global">false</value>
          </record>
          <record javaclass="com.wm.util.Values">
            <value name="node_type">record</value>
            <record name="node_hints" javaclass="com.wm.util.Values">
              <value name="field_usereditable">false</value>
              <value name="field_largerEditor">false</value>
              <value name="field_password">false</value>
            </record>
            <value name="is_public">false</value>
            <value name="field_name">resultAsArray</value>
            <value name="field_type">string</value>
            <value name="field_dim">0</value>
            <array name="field_options" type="value" depth="1">
              <value>false</value>
              <value>true</value>
            </array>
            <value name="nillable">true</value>
            <value name="form_qualified">false</value>
            <value name="is_global">false</value>
          </record>
        </array>
        <value name="rec_closed">true</value>
        <value name="modifiable">true</value>
      </record>
    </array>
    <value name="modifiable">true</value>
  </record>
</Values>
</MAPTARGET>
  <MAPSOURCE>

<Values version="2.0">
  <record name="xml" javaclass="com.wm.util.Values">
    <value name="node_type">record</value>
    <value name="is_public">false</value>
    <value name="field_type">record</value>
    <value name="field_dim">0</value>
    <value name="nillable">true</value>
    <value name="form_qualified">false</value>
    <value name="is_global">false</value>
    <array name="rec_fields" type="record" depth="1">
      <record javaclass="com.wm.util.Values">
        <value name="node_type">unknown</value>
        <value name="is_public">false</value>
        <value name="field_name">ffdata</value>
        <value name="field_type">object</value>
        <value name="field_dim">0</value>
        <value name="nillable">true</value>
        <value name="form_qualified">false</value>
        <value name="is_global">false</value>
      </record>
    </array>
    <value name="modifiable">true</value>
  </record>
</Values>
</MAPSOURCE>

  <!-- nodes -->

<MAPSET NAME="Setter" OVERWRITE="true" VARIABLES="false" FIELD="/ffSchema;1;0">
  <DATA ENCODING="XMLValues" I18N="true">

<Values version="2.0">
  <value name="xml">simpleTestPackage.services.filepolling:ffSchema</value>
  <record name="type" javaclass="com.wm.util.Values">
    <value name="node_type">unknown</value>
    <value name="is_public">false</value>
    <value name="field_name">ffSchema</value>
    <value name="field_type">string</value>
    <value name="field_dim">0</value>
    <value name="nillable">true</value>
    <value name="form_qualified">false</value>
    <value name="is_global">false</value>
  </record>
</Values>
</DATA>
</MAPSET>

<MAPSET NAME="Setter" OVERWRITE="true" VARIABLES="false" FIELD="/iterate;1;0">
  <DATA ENCODING="XMLValues" I18N="true">

<Values version="2.0">
  <value name="xml">false</value>
  <record name="type" javaclass="com.wm.util.Values">
    <value name="node_type">unknown</value>
    <value name="is_public">false</value>
    <value name="field_name">iterate</value>
    <value name="field_type">string</value>
    <value name="field_dim">0</value>
    <value name="field_opt">true</value>
    <array name="field_options" type="value" depth="1">
      <value>false</value>
      <value>true</value>
    </array>
    <value name="nillable">true</value>
    <value name="form_qualified">false</value>
    <value name="is_global">false</value>
  </record>
</Values>
</DATA>
</MAPSET>

<MAPCOPY FROM="/ffdata;3;0" TO="/ffData;3;0">
</MAPCOPY>

<MAPSET NAME="Setter" OVERWRITE="true" VARIABLES="false" FIELD="/flags;2;0/resultAsArray;1;0">
  <DATA ENCODING="XMLValues" I18N="true">

<Values version="2.0">
  <value name="xml">true</value>
  <record name="type" javaclass="com.wm.util.Values">
    <value name="node_type">record</value>
    <record name="node_hints" javaclass="com.wm.util.Values">
      <value name="field_usereditable">false</value>
      <value name="field_largerEditor">false</value>
      <value name="field_password">false</value>
    </record>
    <value name="is_public">false</value>
    <value name="field_name">resultAsArray</value>
    <value name="field_type">string</value>
    <value name="field_dim">0</value>
    <array name="field_options" type="value" depth="1">
      <value>false</value>
      <value>true</value>
    </array>
    <value name="nillable">true</value>
    <value name="form_qualified">false</value>
    <value name="is_global">false</value>
  </record>
</Values>
</DATA>
</MAPSET>

<MAPSET NAME="Setter" OVERWRITE="true" VARIABLES="false" FIELD="/returnErrors;1;0">
  <DATA ENCODING="XMLValues" I18N="true">

<Values version="2.0">
  <value name="xml">asArray</value>
  <record name="type" javaclass="com.wm.util.Values">
    <value name="node_type">unknown</value>
    <value name="is_public">false</value>
    <value name="field_name">returnErrors</value>
    <value name="field_type">string</value>
    <value name="field_dim">0</value>
    <value name="field_opt">true</value>
    <array name="field_options" type="value" depth="1">
      <value>asArray</value>
      <value>inResults</value>
      <value>both</value>
    </array>
    <value name="nillable">true</value>
    <value name="form_qualified">false</value>
    <value name="is_global">false</value>
  </record>
</Values>
</DATA>
</MAPSET>

<MAPSET NAME="Setter" OVERWRITE="true" VARIABLES="false" FIELD="/validate;1;0">
  <DATA ENCODING="XMLValues" I18N="true">

<Values version="2.0">
  <value name="xml">true</value>
  <record name="type" javaclass="com.wm.util.Values">
    <value name="node_type">unknown</value>
    <value name="is_public">false</value>
    <value name="field_name">validate</value>
    <value name="field_type">string</value>
    <value name="field_dim">0</value>
    <value name="field_opt">true</value>
    <array name="field_options" type="value" depth="1">
      <value>false</value>
      <value>true</value>
    </array>
    <value name="nillable">true</value>
    <value name="form_qualified">false</value>
    <value name="is_global">false</value>
  </record>
</Values>
</DATA>
</MAPSET>

<MAPSET NAME="Setter" OVERWRITE="true" VARIABLES="false" FIELD="/encoding;1;0">
  <DATA ENCODING="XMLValues" I18N="true">

<Values version="2.0">
  <value name="xml">UTF8</value>
  <record name="type" javaclass="com.wm.util.Values">
    <value name="node_type">unknown</value>
    <value name="is_public">false</value>
    <value name="field_name">encoding</value>
    <value name="field_type">string</value>
    <value name="field_dim">0</value>
    <value name="field_opt">true</value>
    <value name="nillable">true</value>
    <value name="form_qualified">false</value>
    <value name="is_global">false</value>
  </record>
</Values>
</DATA>
</MAPSET>
</MAP>

<MAP MODE="OUTPUT">
  <MAPTARGET>

<Values version="2.0">
  <record name="xml" javaclass="com.wm.util.Values">
    <value name="node_type">record</value>
    <value name="is_public">false</value>
    <value name="field_type">record</value>
    <value name="field_dim">0</value>
    <value name="nillable">true</value>
    <value name="form_qualified">false</value>
    <value name="is_global">false</value>
    <array name="rec_fields" type="record" depth="1">
      <record javaclass="com.wm.util.Values">
        <value name="node_type">unknown</value>
        <value name="is_public">false</value>
        <value name="field_name">ffData</value>
        <value name="field_type">object</value>
        <value name="field_dim">0</value>
        <value name="nillable">true</value>
        <value name="form_qualified">false</value>
        <value name="is_global">false</value>
      </record>
      <record javaclass="com.wm.util.Values">
        <value name="node_type">unknown</value>
        <value name="is_public">false</value>
        <value name="field_name">ffSchema</value>
        <value name="field_type">string</value>
        <value name="field_dim">0</value>
        <value name="nillable">true</value>
        <value name="form_qualified">false</value>
        <value name="is_global">false</value>
      </record>
      <record javaclass="com.wm.util.Values">
        <value name="node_type">unknown</value>
        <value name="is_public">false</value>
        <value name="field_name">ffdata</value>
        <value name="field_type">object</value>
        <value name="field_dim">0</value>
        <value name="nillable">true</value>
        <value name="form_qualified">false</value>
        <value name="is_global">false</value>
      </record>
      <record javaclass="com.wm.util.Values">
        <value name="node_type">unknown</value>
        <value name="is_public">false</value>
        <value name="field_name">encoding</value>
        <value name="field_type">string</value>
        <value name="field_dim">0</value>
        <value name="nillable">true</value>
        <value name="form_qualified">false</value>
        <value name="is_global">false</value>
      </record>
      <record javaclass="com.wm.util.Values">
        <value name="node_type">unknown</value>
        <value name="is_public">false</value>
        <value name="field_name">$name</value>
        <value name="field_type">string</value>
        <value name="field_dim">0</value>
        <value name="nillable">true</value>
        <value name="form_qualified">false</value>
        <value name="is_global">false</value>
      </record>
      <record javaclass="com.wm.util.Values">
        <value name="node_type">unknown</value>
        <value name="is_public">false</value>
        <value name="field_name">iterate</value>
        <value name="field_type">string</value>
        <value name="field_dim">0</value>
        <value name="nillable">true</value>
        <value name="form_qualified">false</value>
        <value name="is_global">false</value>
      </record>
      <record javaclass="com.wm.util.Values">
        <value name="node_type">unknown</value>
        <value name="is_public">false</value>
        <value name="field_name">validate</value>
        <value name="field_type">string</value>
        <value name="field_dim">0</value>
        <value name="nillable">true</value>
        <value name="form_qualified">false</value>
        <value name="is_global">false</value>
      </record>
      <record javaclass="com.wm.util.Values">
        <value name="node_type">unknown</value>
        <value name="is_public">false</value>
        <value name="field_name">returnErrors</value>
        <value name="field_type">string</value>
        <value name="field_dim">0</value>
        <value name="nillable">true</value>
        <value name="form_qualified">false</value>
        <value name="is_global">false</value>
      </record>
      <record javaclass="com.wm.util.Values">
        <value name="node_type">record</value>
        <value name="is_public">false</value>
        <value name="field_name">flags</value>
        <value name="field_type">record</value>
        <value name="field_dim">0</value>
        <value name="nillable">true</value>
        <value name="form_qualified">false</value>
        <value name="is_global">false</value>
        <array name="rec_fields" type="record" depth="1">
          <record javaclass="com.wm.util.Values">
            <value name="node_type">unknown</value>
            <value name="is_public">false</value>
            <value name="field_name">resultAsArray</value>
            <value name="field_type">string</value>
            <value name="field_dim">0</value>
            <value name="nillable">true</value>
            <value name="form_qualified">false</value>
            <value name="is_global">false</value>
          </record>
        </array>
        <value name="modifiable">true</value>
      </record>
      <record javaclass="com.wm.util.Values">
        <value name="node_type">record</value>
        <value name="is_public">false</value>
        <value name="field_name">ffValues</value>
        <value name="field_type">record</value>
        <value name="field_dim">0</value>
        <value name="nillable">true</value>
        <value name="form_qualified">false</value>
        <value name="is_global">false</value>
        <array name="rec_fields" type="record" depth="1">
        </array>
        <value name="modifiable">true</value>
      </record>
      <record javaclass="com.wm.util.Values">
        <value name="node_type">unknown</value>
        <value name="is_public">false</value>
        <value name="field_name">ffIterator</value>
        <value name="field_type">object</value>
        <value name="field_dim">0</value>
        <value name="field_opt">true</value>
        <value name="nillable">true</value>
        <value name="form_qualified">false</value>
        <value name="is_global">false</value>
      </record>
      <record javaclass="com.wm.util.Values">
        <value name="node_type">unknown</value>
        <value name="is_public">false</value>
        <value name="field_name">isValid</value>
        <value name="field_type">string</value>
        <value name="field_dim">0</value>
        <value name="field_opt">true</value>
        <array name="field_options" type="value" depth="1">
          <value>true</value>
          <value>false</value>
        </array>
        <value name="nillable">true</value>
        <value name="form_qualified">false</value>
        <value name="is_global">false</value>
      </record>
      <record javaclass="com.wm.util.Values">
        <value name="node_type">record</value>
        <value name="is_public">false</value>
        <value name="field_name">errors</value>
        <value name="field_type">record</value>
        <value name="field_dim">1</value>
        <value name="field_opt">true</value>
        <value name="nillable">true</value>
        <value name="form_qualified">false</value>
        <value name="is_global">false</value>
        <value name="is_soap_array_encoding_used">true</value>
        <array name="rec_fields" type="record" depth="1">
        </array>
        <value name="modifiable">true</value>
      </record>
    </array>
    <value name="modifiable">true</value>
  </record>
</Values>
</MAPTARGET>
  <MAPSOURCE>

<Values version="2.0">
  <record name="xml" javaclass="com.wm.util.Values">
    <value name="node_type">record</value>
    <value name="is_public">false</value>
    <value name="field_name">convertToValuesOutput</value>
    <value name="field_type">record</value>
    <value name="field_dim">0</value>
    <value name="nillable">true</value>
    <value name="form_qualified">false</value>
    <value name="is_global">false</value>
    <array name="rec_fields" type="record" depth="1">
      <record javaclass="com.wm.util.Values">
        <value name="node_type">record</value>
        <value name="is_public">false</value>
        <value name="field_name">ffValues</value>
        <value name="field_type">record</value>
        <value name="field_dim">0</value>
        <value name="nillable">true</value>
        <value name="form_qualified">false</value>
        <value name="is_global">false</value>
        <array name="rec_fields" type="record" depth="1">
        </array>
        <value name="modifiable">true</value>
      </record>
      <record javaclass="com.wm.util.Values">
        <value name="node_type">unknown</value>
        <value name="is_public">false</value>
        <value name="field_name">ffIterator</value>
        <value name="field_type">object</value>
        <value name="field_dim">0</value>
        <value name="field_opt">true</value>
        <value name="nillable">true</value>
        <value name="form_qualified">false</value>
        <value name="is_global">false</value>
      </record>
      <record javaclass="com.wm.util.Values">
        <value name="node_type">unknown</value>
        <value name="is_public">false</value>
        <value name="field_name">isValid</value>
        <value name="field_type">string</value>
        <value name="field_dim">0</value>
        <value name="field_opt">true</value>
        <array name="field_options" type="value" depth="1">
          <value>true</value>
          <value>false</value>
        </array>
        <value name="nillable">true</value>
        <value name="form_qualified">false</value>
        <value name="is_global">false</value>
      </record>
      <record javaclass="com.wm.util.Values">
        <value name="node_type">record</value>
        <value name="is_public">false</value>
        <value name="field_name">errors</value>
        <value name="field_type">record</value>
        <value name="field_dim">1</value>
        <value name="field_opt">true</value>
        <value name="nillable">true</value>
        <value name="form_qualified">false</value>
        <value name="is_global">false</value>
        <value name="is_soap_array_encoding_used">true</value>
        <array name="rec_fields" type="record" depth="1">
        </array>
        <value name="modifiable">true</value>
      </record>
    </array>
    <value name="modifiable">true</value>
  </record>
</Values>
</MAPSOURCE>

  <!-- nodes -->

<MAPDELETE FIELD="/ffData;3;0">
</MAPDELETE>

<MAPDELETE FIELD="/ffSchema;1;0">
</MAPDELETE>

<MAPDELETE FIELD="/$name;1;0">
</MAPDELETE>

<MAPDELETE FIELD="/iterate;1;0">
</MAPDELETE>

<MAPDELETE FIELD="/ffdata;3;0">
</MAPDELETE>

<MAPDELETE FIELD="/ffIterator;3;0">
</MAPDELETE>

<MAPDELETE FIELD="/encoding;1;0">
</MAPDELETE>

<MAPDELETE FIELD="/validate;1;0">
</MAPDELETE>

<MAPDELETE FIELD="/returnErrors;1;0">
</MAPDELETE>

<MAPDELETE FIELD="/flags;2;0">
</MAPDELETE>

<MAPDELETE FIELD="/isValid;1;0">
</MAPDELETE>

<MAPDELETE FIELD="/errors;2;1">
</MAPDELETE>
</MAP>
</INVOKE>

<MAP TIMEOUT="" MODE="STANDALONE">
  <COMMENT>map to DT document type</COMMENT>
  <MAPTARGET>

<Values version="2.0">
  <record name="xml" javaclass="com.wm.util.Values">
    <value name="node_type">record</value>
    <value name="is_public">false</value>
    <value name="field_type">record</value>
    <value name="field_dim">0</value>
    <value name="nillable">true</value>
    <value name="form_qualified">false</value>
    <value name="is_global">false</value>
    <array name="rec_fields" type="record" depth="1">
      <record javaclass="com.wm.util.Values">
        <value name="node_type">record</value>
        <value name="is_public">false</value>
        <value name="field_name">ffValues</value>
        <value name="field_type">record</value>
        <value name="field_dim">0</value>
        <value name="nillable">true</value>
        <value name="form_qualified">false</value>
        <value name="is_global">false</value>
        <array name="rec_fields" type="record" depth="1">
        </array>
        <value name="modifiable">true</value>
      </record>
      <record javaclass="com.wm.util.Values">
        <value name="node_type">record</value>
        <value name="is_public">false</value>
        <value name="field_name">ffSchemaDT</value>
        <value name="field_type">recref</value>
        <value name="field_dim">0</value>
        <value name="nillable">true</value>
        <value name="form_qualified">false</value>
        <value name="is_global">false</value>
        <value name="modifiable">true</value>
        <value name="rec_ref">simpleTestPackage.services.filepolling:ffSchemaDT</value>
      </record>
    </array>
    <value name="modifiable">true</value>
  </record>
</Values>
</MAPTARGET>
  <MAPSOURCE>

<Values version="2.0">
  <record name="xml" javaclass="com.wm.util.Values">
    <value name="node_type">record</value>
    <value name="is_public">false</value>
    <value name="field_type">record</value>
    <value name="field_dim">0</value>
    <value name="nillable">true</value>
    <value name="form_qualified">false</value>
    <value name="is_global">false</value>
    <array name="rec_fields" type="record" depth="1">
      <record javaclass="com.wm.util.Values">
        <value name="node_type">record</value>
        <value name="is_public">false</value>
        <value name="field_name">ffValues</value>
        <value name="field_type">record</value>
        <value name="field_dim">0</value>
        <value name="nillable">true</value>
        <value name="form_qualified">false</value>
        <value name="is_global">false</value>
        <array name="rec_fields" type="record" depth="1">
        </array>
        <value name="modifiable">true</value>
      </record>
    </array>
    <value name="modifiable">true</value>
  </record>
</Values>
</MAPSOURCE>

  <!-- nodes -->

<MAPCOPY FROM="/ffValues;2;0" TO="/ffSchemaDT;4;0;simpleTestPackage.services.filepolling:ffSchemaDT">
</MAPCOPY>

<MAPDELETE FIELD="/ffValues;2;0">
</MAPDELETE>
</MAP>

<MAP TIMEOUT="" MODE="STANDALONE">
  <COMMENT>init list of invalid values</COMMENT>
  <MAPTARGET>

<Values version="2.0">
  <record name="xml" javaclass="com.wm.util.Values">
    <value name="node_type">record</value>
    <value name="is_public">false</value>
    <value name="field_type">record</value>
    <value name="field_dim">0</value>
    <value name="nillable">true</value>
    <value name="form_qualified">false</value>
    <value name="is_global">false</value>
    <array name="rec_fields" type="record" depth="1">
      <record javaclass="com.wm.util.Values">
        <value name="node_type">record</value>
        <value name="is_public">false</value>
        <value name="field_name">ffSchemaDT</value>
        <value name="field_type">recref</value>
        <value name="field_dim">0</value>
        <value name="nillable">true</value>
        <value name="form_qualified">false</value>
        <value name="is_global">false</value>
        <value name="modifiable">true</value>
        <value name="rec_ref">simpleTestPackage.services.filepolling:ffSchemaDT</value>
      </record>
      <record javaclass="com.wm.util.Values">
        <value name="node_type">record</value>
        <value name="is_public">false</value>
        <value name="field_name">invaidRecordList</value>
        <value name="field_type">recref</value>
        <value name="field_dim">1</value>
        <value name="nillable">true</value>
        <value name="form_qualified">false</value>
        <value name="is_global">false</value>
        <value name="is_soap_array_encoding_used">false</value>
        <value name="rec_closed">true</value>
        <value name="modifiable">true</value>
        <value name="rec_ref">simpleTestPackage.documents.flatfile:invalidRecord</value>
      </record>
    </array>
    <value name="modifiable">true</value>
  </record>
</Values>
</MAPTARGET>
  <MAPSOURCE>

<Values version="2.0">
  <record name="xml" javaclass="com.wm.util.Values">
    <value name="node_type">record</value>
    <value name="is_public">false</value>
    <value name="field_type">record</value>
    <value name="field_dim">0</value>
    <value name="nillable">true</value>
    <value name="form_qualified">false</value>
    <value name="is_global">false</value>
    <array name="rec_fields" type="record" depth="1">
    </array>
    <value name="modifiable">true</value>
  </record>
</Values>
</MAPSOURCE>

  <!-- nodes -->

<MAPSET NAME="Setter" OVERWRITE="true" VARIABLES="false" FIELD="/invaidRecordList;4;1;simpleTestPackage.documents.flatfile:invalidRecord">
  <DATA ENCODING="XMLValues" I18N="true">

<Values version="2.0">
  <array name="xml" type="record" depth="1">
  </array>
</Values>
</DATA>
</MAPSET>
</MAP>

<LOOP TIMEOUT="" IN-ARRAY="/ffSchemaDT/recordWithNoID">
  <COMMENT></COMMENT>

  <!-- nodes -->

<MAP TIMEOUT="" MODE="STANDALONE">
  <COMMENT>map to address document type</COMMENT>
  <MAPTARGET>

<Values version="2.0">
  <record name="xml" javaclass="com.wm.util.Values">
    <value name="node_type">record</value>
    <value name="is_public">false</value>
    <value name="field_type">record</value>
    <value name="field_dim">0</value>
    <value name="nillable">true</value>
    <value name="form_qualified">false</value>
    <value name="is_global">false</value>
    <array name="rec_fields" type="record" depth="1">
      <record javaclass="com.wm.util.Values">
        <value name="node_type">unknown</value>
        <value name="is_public">false</value>
        <value name="field_name">message</value>
        <value name="field_type">string</value>
        <value name="field_dim">0</value>
        <value name="nillable">true</value>
        <value name="form_qualified">false</value>
        <value name="is_global">false</value>
      </record>
      <record javaclass="com.wm.util.Values">
        <value name="node_type">record</value>
        <value name="is_public">false</value>
        <value name="field_name">ffSchemaDT</value>
        <value name="field_type">recref</value>
        <value name="field_dim">0</value>
        <value name="nillable">true</value>
        <value name="form_qualified">false</value>
        <value name="is_global">false</value>
        <value name="modifiable">true</value>
        <value name="rec_ref">simpleTestPackage.services.filepolling:ffSchemaDT</value>
      </record>
      <record javaclass="com.wm.util.Values">
        <value name="node_type">record</value>
        <value name="is_public">false</value>
        <value name="field_name">address</value>
        <value name="field_type">recref</value>
        <value name="field_dim">0</value>
        <value name="nillable">true</value>
        <value name="form_qualified">false</value>
        <value name="is_global">false</value>
        <value name="rec_closed">true</value>
        <value name="modifiable">true</value>
        <value name="rec_ref">simpleTestPackage.documents:address</value>
      </record>
    </array>
    <value name="modifiable">true</value>
  </record>
</Values>
</MAPTARGET>
  <MAPSOURCE>

<Values version="2.0">
  <record name="xml" javaclass="com.wm.util.Values">
    <value name="node_type">record</value>
    <value name="is_public">false</value>
    <value name="field_type">record</value>
    <value name="field_dim">0</value>
    <value name="nillable">true</value>
    <value name="form_qualified">false</value>
    <value name="is_global">false</value>
    <array name="rec_fields" type="record" depth="1">
      <record javaclass="com.wm.util.Values">
        <value name="node_type">unknown</value>
        <value name="is_public">false</value>
        <value name="field_name">message</value>
        <value name="field_type">string</value>
        <value name="field_dim">0</value>
        <value name="nillable">true</value>
        <value name="form_qualified">false</value>
        <value name="is_global">false</value>
      </record>
      <record javaclass="com.wm.util.Values">
        <value name="node_type">record</value>
        <value name="is_public">false</value>
        <value name="field_name">ffSchemaDT</value>
        <value name="field_type">recref</value>
        <value name="field_dim">0</value>
        <value name="nillable">true</value>
        <value name="form_qualified">false</value>
        <value name="is_global">false</value>
        <value name="modifiable">true</value>
        <value name="rec_ref">simpleTestPackage.services.filepolling:ffSchemaDT</value>
      </record>
      <record javaclass="com.wm.util.Values">
        <value name="node_type">unknown</value>
        <value name="is_public">false</value>
        <value name="field_name">$iteration</value>
        <value name="field_type">string</value>
        <value name="field_dim">0</value>
        <value name="nillable">true</value>
        <value name="form_qualified">false</value>
        <value name="is_global">false</value>
      </record>
    </array>
    <value name="modifiable">true</value>
  </record>
</Values>
</MAPSOURCE>

  <!-- nodes -->

<MAPCOPY FROM="/ffSchemaDT;4;0;simpleTestPackage.services.filepolling:ffSchemaDT/recordWithNoID;2;0/name;1;0" TO="/address;4;0;simpleTestPackage.documents:address/name;1;0">
</MAPCOPY>

<MAPCOPY FROM="/ffSchemaDT;4;0;simpleTestPackage.services.filepolling:ffSchemaDT/recordWithNoID;2;0/address;1;0" TO="/address;4;0;simpleTestPackage.documents:address/address;1;0">
</MAPCOPY>

<MAPCOPY FROM="/ffSchemaDT;4;0;simpleTestPackage.services.filepolling:ffSchemaDT/recordWithNoID;2;0/phone;1;0" TO="/address;4;0;simpleTestPackage.documents:address/phone;1;0">
</MAPCOPY>

<MAPCOPY FROM="/ffSchemaDT;4;0;simpleTestPackage.services.filepolling:ffSchemaDT/recordWithNoID;2;0/mail;1;0" TO="/address;4;0;simpleTestPackage.documents:address/mail;1;0">
</MAPCOPY>

<MAPDELETE FIELD="/ffSchemaDT;4;0;simpleTestPackage.services.filepolling:ffSchemaDT">
</MAPDELETE>
</MAP>

<INVOKE TIMEOUT="" SERVICE="simpleTestPackage.implementation.filepolling:validateAddress" VALIDATE-IN="$none" VALIDATE-OUT="$none">
  <COMMENT></COMMENT>

  <!-- nodes -->

<MAP MODE="INPUT">
  <MAPTARGET>

<Values version="2.0">
  <record name="xml" javaclass="com.wm.util.Values">
    <value name="node_type">record</value>
    <value name="node_comment"></value>
    <value name="is_public">false</value>
    <value name="field_type">record</value>
    <value name="field_dim">0</value>
    <value name="nillable">true</value>
    <value name="form_qualified">false</value>
    <value name="is_global">false</value>
    <array name="rec_fields" type="record" depth="1">
      <record javaclass="com.wm.util.Values">
        <value name="node_type">record</value>
        <value name="node_comment"></value>
        <record name="node_hints" javaclass="com.wm.util.Values">
          <value name="field_largerEditor">false</value>
          <value name="field_password">false</value>
        </record>
        <value name="is_public">false</value>
        <value name="field_name">address</value>
        <value name="field_type">recref</value>
        <value name="field_dim">0</value>
        <value name="nillable">true</value>
        <value name="form_qualified">false</value>
        <value name="is_global">false</value>
        <value name="rec_closed">true</value>
        <value name="modifiable">true</value>
        <value name="rec_ref">simpleTestPackage.documents:address</value>
      </record>
    </array>
    <value name="modifiable">true</value>
  </record>
</Values>
</MAPTARGET>
  <MAPSOURCE>

<Values version="2.0">
  <record name="xml" javaclass="com.wm.util.Values">
    <value name="node_type">record</value>
    <value name="is_public">false</value>
    <value name="field_type">record</value>
    <value name="field_dim">0</value>
    <value name="nillable">true</value>
    <value name="form_qualified">false</value>
    <value name="is_global">false</value>
    <array name="rec_fields" type="record" depth="1">
      <record javaclass="com.wm.util.Values">
        <value name="node_type">record</value>
        <value name="is_public">false</value>
        <value name="field_name">invaidRecordList</value>
        <value name="field_type">recref</value>
        <value name="field_dim">1</value>
        <value name="nillable">true</value>
        <value name="form_qualified">false</value>
        <value name="is_global">false</value>
        <value name="is_soap_array_encoding_used">false</value>
        <value name="modifiable">true</value>
        <value name="rec_ref">simpleTestPackage.documents.flatfile:invalidRecord</value>
      </record>
      <record javaclass="com.wm.util.Values">
        <value name="node_type">record</value>
        <value name="is_public">false</value>
        <value name="field_name">address</value>
        <value name="field_type">recref</value>
        <value name="field_dim">0</value>
        <value name="nillable">true</value>
        <value name="form_qualified">false</value>
        <value name="is_global">false</value>
        <value name="modifiable">true</value>
        <value name="rec_ref">simpleTestPackage.documents:address</value>
      </record>
      <record javaclass="com.wm.util.Values">
        <value name="node_type">unknown</value>
        <value name="is_public">false</value>
        <value name="field_name">$iteration</value>
        <value name="field_type">string</value>
        <value name="field_dim">0</value>
        <value name="nillable">true</value>
        <value name="form_qualified">false</value>
        <value name="is_global">false</value>
      </record>
    </array>
    <value name="modifiable">true</value>
  </record>
</Values>
</MAPSOURCE>

  <!-- nodes -->

<MAPCOPY FROM="/address;4;0;simpleTestPackage.documents:address" TO="/address;4;0;simpleTestPackage.documents:address">
</MAPCOPY>
</MAP>

<MAP MODE="OUTPUT">
</MAP>
</INVOKE>

<BRANCH TIMEOUT="" SWITCH="/isValid">
  <COMMENT></COMMENT>

  <!-- nodes -->

<SEQUENCE NAME="true" TIMEOUT="" EXIT-ON="FAILURE">
  <COMMENT></COMMENT>

  <!-- nodes -->

<INVOKE TIMEOUT="" SERVICE="simpleTestPackage.implementation.filepolling:sendAddressToBackend" VALIDATE-IN="$none" VALIDATE-OUT="$none">
  <COMMENT></COMMENT>

  <!-- nodes -->

<MAP MODE="INPUT">
  <MAPTARGET>

<Values version="2.0">
  <record name="xml" javaclass="com.wm.util.Values">
    <value name="node_type">record</value>
    <value name="node_comment"></value>
    <value name="is_public">false</value>
    <value name="field_type">record</value>
    <value name="field_dim">0</value>
    <value name="nillable">true</value>
    <value name="form_qualified">false</value>
    <value name="is_global">false</value>
    <array name="rec_fields" type="record" depth="1">
      <record javaclass="com.wm.util.Values">
        <value name="node_type">record</value>
        <value name="node_comment"></value>
        <record name="node_hints" javaclass="com.wm.util.Values">
          <value name="field_largerEditor">false</value>
          <value name="field_password">false</value>
        </record>
        <value name="is_public">false</value>
        <value name="field_name">address</value>
        <value name="field_type">recref</value>
        <value name="field_dim">0</value>
        <value name="nillable">true</value>
        <value name="form_qualified">false</value>
        <value name="is_global">false</value>
        <value name="rec_closed">true</value>
        <value name="modifiable">true</value>
        <value name="rec_ref">simpleTestPackage.documents:address</value>
      </record>
    </array>
    <value name="modifiable">true</value>
  </record>
</Values>
</MAPTARGET>
  <MAPSOURCE>

<Values version="2.0">
  <record name="xml" javaclass="com.wm.util.Values">
    <value name="node_type">record</value>
    <value name="is_public">false</value>
    <value name="field_type">record</value>
    <value name="field_dim">0</value>
    <value name="nillable">true</value>
    <value name="form_qualified">false</value>
    <value name="is_global">false</value>
    <array name="rec_fields" type="record" depth="1">
      <record javaclass="com.wm.util.Values">
        <value name="node_type">record</value>
        <value name="is_public">false</value>
        <value name="field_name">invaidRecordList</value>
        <value name="field_type">recref</value>
        <value name="field_dim">1</value>
        <value name="nillable">true</value>
        <value name="form_qualified">false</value>
        <value name="is_global">false</value>
        <value name="is_soap_array_encoding_used">false</value>
        <value name="modifiable">true</value>
        <value name="rec_ref">simpleTestPackage.documents.flatfile:invalidRecord</value>
      </record>
      <record javaclass="com.wm.util.Values">
        <value name="node_type">record</value>
        <value name="is_public">false</value>
        <value name="field_name">address</value>
        <value name="field_type">recref</value>
        <value name="field_dim">0</value>
        <value name="nillable">true</value>
        <value name="form_qualified">false</value>
        <value name="is_global">false</value>
        <value name="modifiable">true</value>
        <value name="rec_ref">simpleTestPackage.documents:address</value>
      </record>
      <record javaclass="com.wm.util.Values">
        <value name="node_type">record</value>
        <value name="node_comment"></value>
        <record name="node_hints" javaclass="com.wm.util.Values">
          <value name="field_usereditable">true</value>
          <value name="field_largerEditor">false</value>
          <value name="field_password">false</value>
        </record>
        <value name="is_public">false</value>
        <value name="field_name">isValid</value>
        <value name="field_type">string</value>
        <value name="field_dim">0</value>
        <array name="field_options" type="value" depth="1">
        </array>
        <value name="nillable">true</value>
        <value name="form_qualified">false</value>
        <value name="is_global">false</value>
      </record>
      <record javaclass="com.wm.util.Values">
        <value name="node_type">record</value>
        <value name="node_comment"></value>
        <record name="node_hints" javaclass="com.wm.util.Values">
          <value name="field_usereditable">true</value>
          <value name="field_largerEditor">false</value>
          <value name="field_password">false</value>
        </record>
        <value name="is_public">false</value>
        <value name="field_name">errorMsg</value>
        <value name="field_type">string</value>
        <value name="field_dim">0</value>
        <value name="field_opt">true</value>
        <array name="field_options" type="value" depth="1">
        </array>
        <value name="nillable">true</value>
        <value name="form_qualified">false</value>
        <value name="is_global">false</value>
      </record>
      <record javaclass="com.wm.util.Values">
        <value name="node_type">unknown</value>
        <value name="is_public">false</value>
        <value name="field_name">$iteration</value>
        <value name="field_type">string</value>
        <value name="field_dim">0</value>
        <value name="nillable">true</value>
        <value name="form_qualified">false</value>
        <value name="is_global">false</value>
      </record>
    </array>
    <value name="modifiable">true</value>
  </record>
</Values>
</MAPSOURCE>

  <!-- nodes -->

<MAPCOPY FROM="/address;4;0;simpleTestPackage.documents:address" TO="/address;4;0;simpleTestPackage.documents:address">
</MAPCOPY>
</MAP>

<MAP MODE="OUTPUT">
  <MAPTARGET>

<Values version="2.0">
  <record name="xml" javaclass="com.wm.util.Values">
    <value name="node_type">record</value>
    <value name="is_public">false</value>
    <value name="field_type">record</value>
    <value name="field_dim">0</value>
    <value name="nillable">true</value>
    <value name="form_qualified">false</value>
    <value name="is_global">false</value>
    <array name="rec_fields" type="record" depth="1">
      <record javaclass="com.wm.util.Values">
        <value name="node_type">record</value>
        <value name="is_public">false</value>
        <value name="field_name">invaidRecordList</value>
        <value name="field_type">recref</value>
        <value name="field_dim">1</value>
        <value name="nillable">true</value>
        <value name="form_qualified">false</value>
        <value name="is_global">false</value>
        <value name="is_soap_array_encoding_used">false</value>
        <value name="modifiable">true</value>
        <value name="rec_ref">simpleTestPackage.documents.flatfile:invalidRecord</value>
      </record>
      <record javaclass="com.wm.util.Values">
        <value name="node_type">record</value>
        <value name="is_public">false</value>
        <value name="field_name">address</value>
        <value name="field_type">recref</value>
        <value name="field_dim">0</value>
        <value name="nillable">true</value>
        <value name="form_qualified">false</value>
        <value name="is_global">false</value>
        <value name="modifiable">true</value>
        <value name="rec_ref">simpleTestPackage.documents:address</value>
      </record>
      <record javaclass="com.wm.util.Values">
        <value name="node_type">record</value>
        <value name="node_comment"></value>
        <record name="node_hints" javaclass="com.wm.util.Values">
          <value name="field_usereditable">true</value>
          <value name="field_largerEditor">false</value>
          <value name="field_password">false</value>
        </record>
        <value name="is_public">false</value>
        <value name="field_name">isValid</value>
        <value name="field_type">string</value>
        <value name="field_dim">0</value>
        <array name="field_options" type="value" depth="1">
        </array>
        <value name="nillable">true</value>
        <value name="form_qualified">false</value>
        <value name="is_global">false</value>
      </record>
      <record javaclass="com.wm.util.Values">
        <value name="node_type">record</value>
        <value name="node_comment"></value>
        <record name="node_hints" javaclass="com.wm.util.Values">
          <value name="field_usereditable">true</value>
          <value name="field_largerEditor">false</value>
          <value name="field_password">false</value>
        </record>
        <value name="is_public">false</value>
        <value name="field_name">errorMsg</value>
        <value name="field_type">string</value>
        <value name="field_dim">0</value>
        <value name="field_opt">true</value>
        <array name="field_options" type="value" depth="1">
        </array>
        <value name="nillable">true</value>
        <value name="form_qualified">false</value>
        <value name="is_global">false</value>
      </record>
    </array>
    <value name="modifiable">true</value>
  </record>
</Values>
</MAPTARGET>
  <MAPSOURCE>

<Values version="2.0">
  <record name="xml" javaclass="com.wm.util.Values">
    <value name="node_type">record</value>
    <value name="node_comment"></value>
    <value name="is_public">false</value>
    <value name="field_type">record</value>
    <value name="field_dim">0</value>
    <value name="nillable">true</value>
    <value name="form_qualified">false</value>
    <value name="is_global">false</value>
    <array name="rec_fields" type="record" depth="1">
    </array>
    <value name="modifiable">true</value>
  </record>
</Values>
</MAPSOURCE>

  <!-- nodes -->

<MAPDELETE FIELD="/isValid;1;0">
</MAPDELETE>

<MAPDELETE FIELD="/errorMsg;1;0">
</MAPDELETE>

<MAPDELETE FIELD="/address;4;0;simpleTestPackage.documents:address">
</MAPDELETE>
</MAP>
</INVOKE>
</SEQUENCE>

<SEQUENCE NAME="false" TIMEOUT="" EXIT-ON="FAILURE">
  <COMMENT></COMMENT>

  <!-- nodes -->

<MAP TIMEOUT="" MODE="STANDALONE">
  <COMMENT>create invalid record entry</COMMENT>
  <MAPTARGET>

<Values version="2.0">
  <record name="xml" javaclass="com.wm.util.Values">
    <value name="node_type">record</value>
    <value name="is_public">false</value>
    <value name="field_type">record</value>
    <value name="field_dim">0</value>
    <value name="nillable">true</value>
    <value name="form_qualified">false</value>
    <value name="is_global">false</value>
    <array name="rec_fields" type="record" depth="1">
      <record javaclass="com.wm.util.Values">
        <value name="node_type">record</value>
        <value name="is_public">false</value>
        <value name="field_name">invaidRecordList</value>
        <value name="field_type">recref</value>
        <value name="field_dim">1</value>
        <value name="nillable">true</value>
        <value name="form_qualified">false</value>
        <value name="is_global">false</value>
        <value name="is_soap_array_encoding_used">false</value>
        <value name="modifiable">true</value>
        <value name="rec_ref">simpleTestPackage.documents.flatfile:invalidRecord</value>
      </record>
      <record javaclass="com.wm.util.Values">
        <value name="node_type">record</value>
        <value name="is_public">false</value>
        <value name="field_name">address</value>
        <value name="field_type">recref</value>
        <value name="field_dim">0</value>
        <value name="nillable">true</value>
        <value name="form_qualified">false</value>
        <value name="is_global">false</value>
        <value name="modifiable">true</value>
        <value name="rec_ref">simpleTestPackage.documents:address</value>
      </record>
      <record javaclass="com.wm.util.Values">
        <value name="node_type">record</value>
        <value name="node_comment"></value>
        <record name="node_hints" javaclass="com.wm.util.Values">
          <value name="field_usereditable">true</value>
          <value name="field_largerEditor">false</value>
          <value name="field_password">false</value>
        </record>
        <value name="is_public">false</value>
        <value name="field_name">isValid</value>
        <value name="field_type">string</value>
        <value name="field_dim">0</value>
        <array name="field_options" type="value" depth="1">
        </array>
        <value name="nillable">true</value>
        <value name="form_qualified">false</value>
        <value name="is_global">false</value>
      </record>
      <record javaclass="com.wm.util.Values">
        <value name="node_type">record</value>
        <value name="node_comment"></value>
        <record name="node_hints" javaclass="com.wm.util.Values">
          <value name="field_usereditable">true</value>
          <value name="field_largerEditor">false</value>
          <value name="field_password">false</value>
        </record>
        <value name="is_public">false</value>
        <value name="field_name">errorMsg</value>
        <value name="field_type">string</value>
        <value name="field_dim">0</value>
        <value name="field_opt">true</value>
        <array name="field_options" type="value" depth="1">
        </array>
        <value name="nillable">true</value>
        <value name="form_qualified">false</value>
        <value name="is_global">false</value>
      </record>
      <record javaclass="com.wm.util.Values">
        <value name="node_type">record</value>
        <value name="is_public">false</value>
        <value name="field_name">invalidRecord</value>
        <value name="field_type">recref</value>
        <value name="field_dim">0</value>
        <value name="nillable">true</value>
        <value name="form_qualified">false</value>
        <value name="is_global">false</value>
        <value name="rec_closed">true</value>
        <value name="modifiable">true</value>
        <value name="rec_ref">simpleTestPackage.documents.flatfile:invalidRecord</value>
      </record>
    </array>
    <value name="modifiable">true</value>
  </record>
</Values>
</MAPTARGET>
  <MAPSOURCE>

<Values version="2.0">
  <record name="xml" javaclass="com.wm.util.Values">
    <value name="node_type">record</value>
    <value name="is_public">false</value>
    <value name="field_type">record</value>
    <value name="field_dim">0</value>
    <value name="nillable">true</value>
    <value name="form_qualified">false</value>
    <value name="is_global">false</value>
    <array name="rec_fields" type="record" depth="1">
      <record javaclass="com.wm.util.Values">
        <value name="node_type">record</value>
        <value name="is_public">false</value>
        <value name="field_name">invaidRecordList</value>
        <value name="field_type">recref</value>
        <value name="field_dim">1</value>
        <value name="nillable">true</value>
        <value name="form_qualified">false</value>
        <value name="is_global">false</value>
        <value name="is_soap_array_encoding_used">false</value>
        <value name="modifiable">true</value>
        <value name="rec_ref">simpleTestPackage.documents.flatfile:invalidRecord</value>
      </record>
      <record javaclass="com.wm.util.Values">
        <value name="node_type">record</value>
        <value name="is_public">false</value>
        <value name="field_name">address</value>
        <value name="field_type">recref</value>
        <value name="field_dim">0</value>
        <value name="nillable">true</value>
        <value name="form_qualified">false</value>
        <value name="is_global">false</value>
        <value name="modifiable">true</value>
        <value name="rec_ref">simpleTestPackage.documents:address</value>
      </record>
      <record javaclass="com.wm.util.Values">
        <value name="node_type">record</value>
        <value name="node_comment"></value>
        <record name="node_hints" javaclass="com.wm.util.Values">
          <value name="field_usereditable">true</value>
          <value name="field_largerEditor">false</value>
          <value name="field_password">false</value>
        </record>
        <value name="is_public">false</value>
        <value name="field_name">isValid</value>
        <value name="field_type">string</value>
        <value name="field_dim">0</value>
        <array name="field_options" type="value" depth="1">
        </array>
        <value name="nillable">true</value>
        <value name="form_qualified">false</value>
        <value name="is_global">false</value>
      </record>
      <record javaclass="com.wm.util.Values">
        <value name="node_type">record</value>
        <value name="node_comment"></value>
        <record name="node_hints" javaclass="com.wm.util.Values">
          <value name="field_usereditable">true</value>
          <value name="field_largerEditor">false</value>
          <value name="field_password">false</value>
        </record>
        <value name="is_public">false</value>
        <value name="field_name">errorMsg</value>
        <value name="field_type">string</value>
        <value name="field_dim">0</value>
        <value name="field_opt">true</value>
        <array name="field_options" type="value" depth="1">
        </array>
        <value name="nillable">true</value>
        <value name="form_qualified">false</value>
        <value name="is_global">false</value>
      </record>
      <record javaclass="com.wm.util.Values">
        <value name="node_type">unknown</value>
        <value name="is_public">false</value>
        <value name="field_name">$iteration</value>
        <value name="field_type">string</value>
        <value name="field_dim">0</value>
        <value name="nillable">true</value>
        <value name="form_qualified">false</value>
        <value name="is_global">false</value>
      </record>
    </array>
    <value name="modifiable">true</value>
  </record>
</Values>
</MAPSOURCE>

  <!-- nodes -->

<MAPCOPY FROM="/$iteration;1;0" TO="/invalidRecord;4;0;simpleTestPackage.documents.flatfile:invalidRecord/position;1;0">
</MAPCOPY>

<MAPCOPY FROM="/errorMsg;1;0" TO="/invalidRecord;4;0;simpleTestPackage.documents.flatfile:invalidRecord/msg;1;0">
</MAPCOPY>

<MAPDELETE FIELD="/errorMsg;1;0">
</MAPDELETE>

<MAPDELETE FIELD="/isValid;1;0">
</MAPDELETE>
</MAP>

<INVOKE TIMEOUT="" SERVICE="pub.list:appendToDocumentList" VALIDATE-IN="$none" VALIDATE-OUT="$none">
  <COMMENT></COMMENT>

  <!-- nodes -->

<MAP MODE="INPUT">
  <MAPTARGET>

<Values version="2.0">
  <record name="xml" javaclass="com.wm.util.Values">
    <value name="node_type">record</value>
    <value name="is_public">false</value>
    <value name="field_name">appendToDocumentListInput</value>
    <value name="field_type">record</value>
    <value name="field_dim">0</value>
    <value name="nillable">true</value>
    <value name="form_qualified">false</value>
    <value name="is_global">false</value>
    <array name="rec_fields" type="record" depth="1">
      <record javaclass="com.wm.util.Values">
        <value name="node_type">record</value>
        <value name="is_public">false</value>
        <value name="field_name">toList</value>
        <value name="field_type">record</value>
        <value name="field_dim">1</value>
        <value name="field_opt">true</value>
        <value name="nillable">true</value>
        <value name="form_qualified">false</value>
        <value name="is_global">false</value>
        <value name="is_soap_array_encoding_used">false</value>
        <array name="rec_fields" type="record" depth="1">
        </array>
        <value name="modifiable">true</value>
      </record>
      <record javaclass="com.wm.util.Values">
        <value name="node_type">record</value>
        <value name="is_public">false</value>
        <value name="field_name">fromList</value>
        <value name="field_type">record</value>
        <value name="field_dim">1</value>
        <value name="field_opt">true</value>
        <value name="nillable">true</value>
        <value name="form_qualified">false</value>
        <value name="is_global">false</value>
        <value name="is_soap_array_encoding_used">false</value>
        <array name="rec_fields" type="record" depth="1">
        </array>
        <value name="modifiable">true</value>
      </record>
      <record javaclass="com.wm.util.Values">
        <value name="node_type">record</value>
        <value name="is_public">false</value>
        <value name="field_name">fromItem</value>
        <value name="field_type">record</value>
        <value name="field_dim">0</value>
        <value name="field_opt">true</value>
        <value name="nillable">true</value>
        <value name="form_qualified">false</value>
        <value name="is_global">false</value>
        <array name="rec_fields" type="record" depth="1">
        </array>
        <value name="modifiable">true</value>
      </record>
    </array>
    <value name="modifiable">true</value>
  </record>
</Values>
</MAPTARGET>
  <MAPSOURCE>

<Values version="2.0">
  <record name="xml" javaclass="com.wm.util.Values">
    <value name="node_type">record</value>
    <value name="is_public">false</value>
    <value name="field_type">record</value>
    <value name="field_dim">0</value>
    <value name="nillable">true</value>
    <value name="form_qualified">false</value>
    <value name="is_global">false</value>
    <array name="rec_fields" type="record" depth="1">
      <record javaclass="com.wm.util.Values">
        <value name="node_type">record</value>
        <value name="is_public">false</value>
        <value name="field_name">invaidRecordList</value>
        <value name="field_type">recref</value>
        <value name="field_dim">1</value>
        <value name="nillable">true</value>
        <value name="form_qualified">false</value>
        <value name="is_global">false</value>
        <value name="is_soap_array_encoding_used">false</value>
        <value name="modifiable">true</value>
        <value name="rec_ref">simpleTestPackage.documents.flatfile:invalidRecord</value>
      </record>
      <record javaclass="com.wm.util.Values">
        <value name="node_type">record</value>
        <value name="is_public">false</value>
        <value name="field_name">address</value>
        <value name="field_type">recref</value>
        <value name="field_dim">0</value>
        <value name="nillable">true</value>
        <value name="form_qualified">false</value>
        <value name="is_global">false</value>
        <value name="modifiable">true</value>
        <value name="rec_ref">simpleTestPackage.documents:address</value>
      </record>
      <record javaclass="com.wm.util.Values">
        <value name="node_type">unknown</value>
        <value name="is_public">false</value>
        <value name="field_name">$iteration</value>
        <value name="field_type">string</value>
        <value name="field_dim">0</value>
        <value name="nillable">true</value>
        <value name="form_qualified">false</value>
        <value name="is_global">false</value>
      </record>
      <record javaclass="com.wm.util.Values">
        <value name="node_type">record</value>
        <value name="is_public">false</value>
        <value name="field_name">invalidRecord</value>
        <value name="field_type">recref</value>
        <value name="field_dim">0</value>
        <value name="nillable">true</value>
        <value name="form_qualified">false</value>
        <value name="is_global">false</value>
        <value name="modifiable">true</value>
        <value name="rec_ref">simpleTestPackage.documents.flatfile:invalidRecord</value>
      </record>
    </array>
    <value name="modifiable">true</value>
  </record>
</Values>
</MAPSOURCE>

  <!-- nodes -->

<MAPCOPY FROM="/invalidRecord;4;0;simpleTestPackage.documents.flatfile:invalidRecord" TO="/fromItem;2;0">
</MAPCOPY>

<MAPCOPY FROM="/invaidRecordList;4;1;simpleTestPackage.documents.flatfile:invalidRecord" TO="/toList;2;1">
</MAPCOPY>
</MAP>

<MAP MODE="OUTPUT">
  <MAPTARGET>

<Values version="2.0">
  <record name="xml" javaclass="com.wm.util.Values">
    <value name="node_type">record</value>
    <value name="is_public">false</value>
    <value name="field_type">record</value>
    <value name="field_dim">0</value>
    <value name="nillable">true</value>
    <value name="form_qualified">false</value>
    <value name="is_global">false</value>
    <array name="rec_fields" type="record" depth="1">
      <record javaclass="com.wm.util.Values">
        <value name="node_type">record</value>
        <value name="is_public">false</value>
        <value name="field_name">toList</value>
        <value name="field_type">record</value>
        <value name="field_dim">1</value>
        <value name="nillable">true</value>
        <value name="form_qualified">false</value>
        <value name="is_global">false</value>
        <value name="is_soap_array_encoding_used">false</value>
        <array name="rec_fields" type="record" depth="1">
        </array>
        <value name="modifiable">true</value>
      </record>
      <record javaclass="com.wm.util.Values">
        <value name="node_type">record</value>
        <value name="is_public">false</value>
        <value name="field_name">invaidRecordList</value>
        <value name="field_type">recref</value>
        <value name="field_dim">1</value>
        <value name="nillable">true</value>
        <value name="form_qualified">false</value>
        <value name="is_global">false</value>
        <value name="is_soap_array_encoding_used">false</value>
        <value name="modifiable">true</value>
        <value name="rec_ref">simpleTestPackage.documents.flatfile:invalidRecord</value>
      </record>
      <record javaclass="com.wm.util.Values">
        <value name="node_type">record</value>
        <value name="is_public">false</value>
        <value name="field_name">fromItem</value>
        <value name="field_type">record</value>
        <value name="field_dim">0</value>
        <value name="nillable">true</value>
        <value name="form_qualified">false</value>
        <value name="is_global">false</value>
        <array name="rec_fields" type="record" depth="1">
        </array>
        <value name="modifiable">true</value>
      </record>
      <record javaclass="com.wm.util.Values">
        <value name="node_type">record</value>
        <value name="is_public">false</value>
        <value name="field_name">address</value>
        <value name="field_type">recref</value>
        <value name="field_dim">0</value>
        <value name="nillable">true</value>
        <value name="form_qualified">false</value>
        <value name="is_global">false</value>
        <value name="modifiable">true</value>
        <value name="rec_ref">simpleTestPackage.documents:address</value>
      </record>
      <record javaclass="com.wm.util.Values">
        <value name="node_type">unknown</value>
        <value name="is_public">false</value>
        <value name="field_name">$iteration</value>
        <value name="field_type">string</value>
        <value name="field_dim">0</value>
        <value name="nillable">true</value>
        <value name="form_qualified">false</value>
        <value name="is_global">false</value>
      </record>
      <record javaclass="com.wm.util.Values">
        <value name="node_type">record</value>
        <value name="is_public">false</value>
        <value name="field_name">invalidRecord</value>
        <value name="field_type">recref</value>
        <value name="field_dim">0</value>
        <value name="nillable">true</value>
        <value name="form_qualified">false</value>
        <value name="is_global">false</value>
        <value name="modifiable">true</value>
        <value name="rec_ref">simpleTestPackage.documents.flatfile:invalidRecord</value>
      </record>
    </array>
    <value name="modifiable">true</value>
  </record>
</Values>
</MAPTARGET>
  <MAPSOURCE>

<Values version="2.0">
  <record name="xml" javaclass="com.wm.util.Values">
    <value name="node_type">record</value>
    <value name="is_public">false</value>
    <value name="field_name">appendToDocumentListOutput</value>
    <value name="field_type">record</value>
    <value name="field_dim">0</value>
    <value name="nillable">true</value>
    <value name="form_qualified">false</value>
    <value name="is_global">false</value>
    <array name="rec_fields" type="record" depth="1">
      <record javaclass="com.wm.util.Values">
        <value name="node_type">record</value>
        <value name="is_public">false</value>
        <value name="field_name">toList</value>
        <value name="field_type">record</value>
        <value name="field_dim">1</value>
        <value name="nillable">true</value>
        <value name="form_qualified">false</value>
        <value name="is_global">false</value>
        <value name="is_soap_array_encoding_used">false</value>
        <array name="rec_fields" type="record" depth="1">
        </array>
        <value name="modifiable">true</value>
      </record>
    </array>
    <value name="modifiable">true</value>
  </record>
</Values>
</MAPSOURCE>

  <!-- nodes -->

<MAPCOPY FROM="/toList;2;1" TO="/invaidRecordList;4;1;simpleTestPackage.documents.flatfile:invalidRecord">
</MAPCOPY>

<MAPDELETE FIELD="/toList;2;1">
</MAPDELETE>

<MAPDELETE FIELD="/fromItem;2;0">
</MAPDELETE>

<MAPDELETE FIELD="/invalidRecord;4;0;simpleTestPackage.documents.flatfile:invalidRecord">
</MAPDELETE>
</MAP>
</INVOKE>
</SEQUENCE>
</BRANCH>
</LOOP>

<INVOKE TIMEOUT="" SERVICE="simpleTestPackage.implementation.filepolling:writeErrorFile" VALIDATE-IN="$none" VALIDATE-OUT="$none">
  <COMMENT></COMMENT>

  <!-- nodes -->

<MAP MODE="INPUT">
  <MAPTARGET>

<Values version="2.0">
  <record name="xml" javaclass="com.wm.util.Values">
    <value name="node_type">record</value>
    <value name="node_comment"></value>
    <value name="is_public">false</value>
    <value name="field_type">record</value>
    <value name="field_dim">0</value>
    <value name="nillable">true</value>
    <value name="form_qualified">false</value>
    <value name="is_global">false</value>
    <array name="rec_fields" type="record" depth="1">
      <record javaclass="com.wm.util.Values">
        <value name="node_type">record</value>
        <value name="node_comment"></value>
        <record name="node_hints" javaclass="com.wm.util.Values">
          <value name="field_largerEditor">false</value>
          <value name="field_password">false</value>
        </record>
        <value name="is_public">false</value>
        <value name="field_name">invalidRecordList</value>
        <value name="field_type">recref</value>
        <value name="field_dim">1</value>
        <value name="nillable">true</value>
        <value name="form_qualified">false</value>
        <value name="is_global">false</value>
        <value name="is_soap_array_encoding_used">false</value>
        <value name="rec_closed">true</value>
        <value name="modifiable">true</value>
        <value name="rec_ref">simpleTestPackage.documents.flatfile:invalidRecord</value>
      </record>
      <record javaclass="com.wm.util.Values">
        <value name="node_type">record</value>
        <value name="node_comment"></value>
        <record name="node_hints" javaclass="com.wm.util.Values">
          <value name="field_usereditable">true</value>
          <value name="field_largerEditor">false</value>
          <value name="field_password">false</value>
        </record>
        <value name="is_public">false</value>
        <value name="field_name">inboundFile</value>
        <value name="field_type">string</value>
        <value name="field_dim">0</value>
        <array name="field_options" type="value" depth="1">
        </array>
        <value name="nillable">true</value>
        <value name="form_qualified">false</value>
        <value name="is_global">false</value>
      </record>
    </array>
    <value name="modifiable">true</value>
  </record>
</Values>
</MAPTARGET>
  <MAPSOURCE>

<Values version="2.0">
  <record name="xml" javaclass="com.wm.util.Values">
    <value name="node_type">record</value>
    <value name="is_public">false</value>
    <value name="field_type">record</value>
    <value name="field_dim">0</value>
    <value name="nillable">true</value>
    <value name="form_qualified">false</value>
    <value name="is_global">false</value>
    <array name="rec_fields" type="record" depth="1">
      <record javaclass="com.wm.util.Values">
        <value name="node_type">record</value>
        <value name="is_public">false</value>
        <value name="field_name">invaidRecordList</value>
        <value name="field_type">recref</value>
        <value name="field_dim">1</value>
        <value name="nillable">true</value>
        <value name="form_qualified">false</value>
        <value name="is_global">false</value>
        <value name="is_soap_array_encoding_used">false</value>
        <value name="modifiable">true</value>
        <value name="rec_ref">simpleTestPackage.documents.flatfile:invalidRecord</value>
      </record>
      <record javaclass="com.wm.util.Values">
        <value name="node_type">record</value>
        <value name="is_public">false</value>
        <value name="field_name">address</value>
        <value name="field_type">recref</value>
        <value name="field_dim">0</value>
        <value name="nillable">true</value>
        <value name="form_qualified">false</value>
        <value name="is_global">false</value>
        <value name="modifiable">true</value>
        <value name="rec_ref">simpleTestPackage.documents:address</value>
      </record>
      <record javaclass="com.wm.util.Values">
        <value name="node_type">unknown</value>
        <value name="is_public">false</value>
        <value name="field_name">$iteration</value>
        <value name="field_type">string</value>
        <value name="field_dim">0</value>
        <value name="nillable">true</value>
        <value name="form_qualified">false</value>
        <value name="is_global">false</value>
      </record>
    </array>
    <value name="modifiable">true</value>
  </record>
</Values>
</MAPSOURCE>

  <!-- nodes -->

<MAPCOPY FROM="/invaidRecordList;4;1;simpleTestPackage.documents.flatfile:invalidRecord" TO="/invalidRecordList;4;1;simpleTestPackage.documents.flatfile:invalidRecord">
</MAPCOPY>

<MAPSET NAME="Setter" OVERWRITE="true" VARIABLES="true" FIELD="/inboundFile;1;0">
  <DATA ENCODING="XMLValues" I18N="true">

<Values version="2.0">
  <value name="xml">%originalFileName%	
</value>
  <record name="type" javaclass="com.wm.util.Values">
    <value name="node_type">record</value>
    <value name="node_comment"></value>
    <record name="node_hints" javaclass="com.wm.util.Values">
      <value name="field_usereditable">true</value>
      <value name="field_largerEditor">false</value>
      <value name="field_password">false</value>
    </record>
    <value name="is_public">false</value>
    <value name="field_name">inboundFile</value>
    <value name="field_type">string</value>
    <value name="field_dim">0</value>
    <array name="field_options" type="value" depth="1">
    </array>
    <value name="nillable">true</value>
    <value name="form_qualified">false</value>
    <value name="is_global">false</value>
  </record>
</Values>
</DATA>
</MAPSET>
</MAP>

<MAP MODE="OUTPUT">
  <MAPTARGET>

<Values version="2.0">
  <record name="xml" javaclass="com.wm.util.Values">
    <value name="node_type">record</value>
    <value name="is_public">false</value>
    <value name="field_type">record</value>
    <value name="field_dim">0</value>
    <value name="nillable">true</value>
    <value name="form_qualified">false</value>
    <value name="is_global">false</value>
    <array name="rec_fields" type="record" depth="1">
      <record javaclass="com.wm.util.Values">
        <value name="node_type">record</value>
        <value name="is_public">false</value>
        <value name="field_name">invalidRecordList</value>
        <value name="field_type">recref</value>
        <value name="field_dim">1</value>
        <value name="nillable">true</value>
        <value name="form_qualified">false</value>
        <value name="is_global">false</value>
        <value name="is_soap_array_encoding_used">false</value>
        <value name="modifiable">true</value>
        <value name="rec_ref">simpleTestPackage.documents.flatfile:invalidRecord</value>
      </record>
      <record javaclass="com.wm.util.Values">
        <value name="node_type">unknown</value>
        <value name="is_public">false</value>
        <value name="field_name">inboundFile</value>
        <value name="field_type">string</value>
        <value name="field_dim">0</value>
        <value name="nillable">true</value>
        <value name="form_qualified">false</value>
        <value name="is_global">false</value>
      </record>
      <record javaclass="com.wm.util.Values">
        <value name="node_type">record</value>
        <value name="is_public">false</value>
        <value name="field_name">invaidRecordList</value>
        <value name="field_type">recref</value>
        <value name="field_dim">1</value>
        <value name="nillable">true</value>
        <value name="form_qualified">false</value>
        <value name="is_global">false</value>
        <value name="is_soap_array_encoding_used">false</value>
        <value name="modifiable">true</value>
        <value name="rec_ref">simpleTestPackage.documents.flatfile:invalidRecord</value>
      </record>
      <record javaclass="com.wm.util.Values">
        <value name="node_type">record</value>
        <value name="is_public">false</value>
        <value name="field_name">address</value>
        <value name="field_type">recref</value>
        <value name="field_dim">0</value>
        <value name="nillable">true</value>
        <value name="form_qualified">false</value>
        <value name="is_global">false</value>
        <value name="modifiable">true</value>
        <value name="rec_ref">simpleTestPackage.documents:address</value>
      </record>
      <record javaclass="com.wm.util.Values">
        <value name="node_type">unknown</value>
        <value name="is_public">false</value>
        <value name="field_name">$iteration</value>
        <value name="field_type">string</value>
        <value name="field_dim">0</value>
        <value name="nillable">true</value>
        <value name="form_qualified">false</value>
        <value name="is_global">false</value>
      </record>
    </array>
    <value name="modifiable">true</value>
  </record>
</Values>
</MAPTARGET>
  <MAPSOURCE>

<Values version="2.0">
  <record name="xml" javaclass="com.wm.util.Values">
    <value name="node_type">record</value>
    <value name="node_comment"></value>
    <value name="is_public">false</value>
    <value name="field_type">record</value>
    <value name="field_dim">0</value>
    <value name="nillable">true</value>
    <value name="form_qualified">false</value>
    <value name="is_global">false</value>
    <array name="rec_fields" type="record" depth="1">
    </array>
    <value name="modifiable">true</value>
  </record>
</Values>
</MAPSOURCE>

  <!-- nodes -->

<MAPDELETE FIELD="/invalidRecordList;4;1;simpleTestPackage.documents.flatfile:invalidRecord">
</MAPDELETE>

<MAPDELETE FIELD="/inboundFile;1;0">
</MAPDELETE>

<MAPDELETE FIELD="/invaidRecordList;4;1;simpleTestPackage.documents.flatfile:invalidRecord">
</MAPDELETE>

<MAPDELETE FIELD="/address;4;0;simpleTestPackage.documents:address">
</MAPDELETE>

<MAPDELETE FIELD="/$iteration;1;0">
</MAPDELETE>
</MAP>
</INVOKE>
</FLOW>
